changelist_init/__init__.py
changelist_init/__main__.py
changelist_init/data/__init__.py
changelist_init/data/fc_to_cl_map.py
changelist_init/git/__init__.py
changelist_init/git/status_change_mapping.py
changelist_init/git/status_reader.py
changelist_init/git/status_runner.py
changelist_init/input/__init__.py
changelist_init/input/argument_parser.py
changelist_init/input/input_data.py
changelist_init-0.4.dist-info/licenses/LICENSE
changelist_init-0.4.dist-info/METADATA
changelist_init-0.4.dist-info/WHEEL
changelist_init-0.4.dist-info/entry_points.txt
changelist_init-0.4.dist-info/top_level.txt
changelist_init-0.4.dist-info/RECORD
