Metadata-Version: 2.4
Name: changelist-init
Version: 0.4
Summary: Initialize and update Changelists information.
Home-page: https://github.com/DK96-OS/changelist-init/
Author: DK96-OS
License: GPLv3
Project-URL: Issues, https://github.com/DK96-OS/changelist-init/issues
Project-URL: Source Code, https://github.com/DK96-OS/changelist-init/
Keywords: vcs,foci,changelist,git
Classifier: Natural Language :: English
Classifier: Operating System :: OS Independent
Classifier: Intended Audience :: Developers
Classifier: License :: OSI Approved :: GNU General Public License v3 (GPLv3)
Classifier: Programming Language :: Python :: 3
Classifier: Programming Language :: Python :: 3.10
Classifier: Programming Language :: Python :: 3.11
Classifier: Programming Language :: Python :: 3.12
Classifier: Programming Language :: Python :: 3.13
Classifier: Programming Language :: Python :: 3.14
Requires-Python: >=3.10
License-File: LICENSE
Requires-Dist: changelist-data<0.4,>=0.2.5
Dynamic: author
Dynamic: classifier
Dynamic: description
Dynamic: description-content-type
Dynamic: home-page
Dynamic: keywords
Dynamic: license
Dynamic: license-file
Dynamic: project-url
Dynamic: requires-dist
Dynamic: requires-python
Dynamic: summary
